metamorphosis/__init__.py
metamorphosis/events.py
metamorphosis/gregor.py
metamorphosis/microservice.py
metamorphosis/mutations.py
metamorphosis/node.py
metamorphosis/service_web.py
metamorphosis/celery/__init__.py
metamorphosis/celery/microservice.py
metamorphosis/celery/mutations.py
metamorphosis/celery/example/__init__.py
metamorphosis/celery/example/app.py
metamorphosis/celery/example/models.py
metamorphosis/celery/example/service.py
metamorphosis/example/__init__.py
metamorphosis/example/app.py
metamorphosis/example/models.py
metamorphosis/example/service.py
tests/__init__.py
tests/test_consumer_group.py
tests/test_events.py
tests/test_kafka_microservice.py
tests/test_mutations.py
metamorphosis-0.4.5.dist-info/LICENSE
metamorphosis-0.4.5.dist-info/METADATA
metamorphosis-0.4.5.dist-info/WHEEL
metamorphosis-0.4.5.dist-info/entry_points.txt
metamorphosis-0.4.5.dist-info/top_level.txt
metamorphosis-0.4.5.dist-info/RECORD
