Metadata-Version: 2.1
Name: metamorphosis
Version: 0.4.5
Summary: An opinionated event streaming microframework
Home-page: https://teamworksapp.gitlab.com/jheard/metamorphosis
Author: Jefferson Heard
Author-email: jheard@teamworks.com
License: MIT
Platform: UNKNOWN
Classifier: Programming Language :: Python :: 3
Classifier: License :: OSI Approved :: MIT License
Classifier: Operating System :: OS Independent
Requires-Python: >=3.6
Requires-Dist: psutil
Requires-Dist: click
Requires-Dist: redis
Requires-Dist: graphene (>=2.1.0)
Requires-Dist: graphql-core (>=2.1.0)
Requires-Dist: kafka-python (>=1.4.7)
Requires-Dist: msgpack (==0.6.2)
Requires-Dist: Werkzeug (>=0.14.0)
Requires-Dist: Flask (>=1.0.3)
